kube_custom_resource/__init__.py
kube_custom_resource/custom_resource.py
kube_custom_resource/generate.py
kube_custom_resource/registry.py
kube_custom_resource/schema.py
kube_custom_resource-0.6.1.dist-info/LICENSE
kube_custom_resource-0.6.1.dist-info/METADATA
kube_custom_resource-0.6.1.dist-info/WHEEL
kube_custom_resource-0.6.1.dist-info/entry_points.txt
kube_custom_resource-0.6.1.dist-info/top_level.txt
kube_custom_resource-0.6.1.dist-info/RECORD
